nonebot_plugin_yulu/__init__.py
nonebot_plugin_yulu/jitang.txt
nonebot_plugin_yulu/yiyan.txt
nonebot_plugin_yulu-3.0.dist-info/METADATA
nonebot_plugin_yulu-3.0.dist-info/WHEEL
nonebot_plugin_yulu-3.0.dist-info/top_level.txt
nonebot_plugin_yulu-3.0.dist-info/RECORD
