Metadata-Version: 2.1
Name: nonebot-plugin-yulu
Version: 3.0
Summary: 语录娱乐小插件
Home-page: https://github.com/bingqiu456/nonebot_plugin_yulu
Author: bingyue
Author-email: hello-yiqiu@qq.com
License: UNKNOWN
Keywords: nonebot_plugin_yulu,nonebot,nonebot_plugin
Platform: UNKNOWN
Requires-Dist: bs4 (>=0.0.1)
Requires-Dist: beautifulsoup4 (>=4.11.1)
Requires-Dist: nonebot2 (>=2.0.0b2)
Requires-Dist: nonebot-adapter-onebot (>=2.0.0b1)
Requires-Dist: httpx (==0.23.1)
